g2p_mix/__init__.py
g2p_mix/cli.py
g2p_mix/constants.py
g2p_mix/g2p_eng.py
g2p_mix/g2p_mix.py
g2p_mix/token.py
g2p_mix/tokenizer.py
g2p_mix/tone_sandhi.py
g2p_mix/utils.py
g2p_mix/dict/digits.txt
g2p_mix/dict/interjections.txt
g2p_mix/dict/ipa.json
g2p_mix/dict/neural_tone_words.txt
g2p_mix/dict/phones.json
g2p_mix/dict/phrases.txt
g2p_mix/dict/pos.json
g2p_mix/dict/single.txt
g2p_mix/dict/whitelist.txt
g2p_mix/nltk_data/corpora/cmudict.zip
g2p_mix/nltk_data/taggers/averaged_perceptron_tagger.zip
g2p_mix/nltk_data/taggers/averaged_perceptron_tagger_eng/averaged_perceptron_tagger_eng.classes.json
g2p_mix/nltk_data/taggers/averaged_perceptron_tagger_eng/averaged_perceptron_tagger_eng.tagdict.json
g2p_mix/nltk_data/taggers/averaged_perceptron_tagger_eng/averaged_perceptron_tagger_eng.weights.json
g2p_mix-0.6.4.dist-info/LICENSE
g2p_mix-0.6.4.dist-info/METADATA
g2p_mix-0.6.4.dist-info/WHEEL
g2p_mix-0.6.4.dist-info/entry_points.txt
g2p_mix-0.6.4.dist-info/top_level.txt
g2p_mix-0.6.4.dist-info/RECORD
