Metadata-Version: 2.2
Name: g2p-mix
Version: 0.6.4
Summary: G2P mix
Home-page: https://github.com/pengzhendong/g2p-mix
Author: Zhendong Peng
Author-email: pzd17@tsinghua.org.cn
Classifier: Programming Language :: Python :: 3
Classifier: Operating System :: OS Independent
Classifier: Topic :: Scientific/Engineering
License-File: LICENSE
Requires-Dist: g2p_en
Requires-Dist: jieba
Requires-Dist: pycantonese
Requires-Dist: pyopenhc
Requires-Dist: pypinyin
Requires-Dist: pypinyin-dict
Requires-Dist: wetext
Requires-Dist: wordsegment
Provides-Extra: g2pw
Requires-Dist: torch; extra == "g2pw"
Requires-Dist: modelscope; extra == "g2pw"
Requires-Dist: pypinyin-g2pw; extra == "g2pw"
Dynamic: author
Dynamic: author-email
Dynamic: classifier
Dynamic: description
Dynamic: description-content-type
Dynamic: home-page
Dynamic: provides-extra
Dynamic: requires-dist
Dynamic: summary
